Metadata-Version: 2.1
Name: ADVECTOR
Version: 1.0.1
Summary: A computationally efficient and massively parallel marine litter transport model
Home-page: https://github.com/TheOceanCleanupAlgorithms/ADVECTOR
Author: Doug Klink
Author-email: dougdklink3@gmail.com
License: UNKNOWN
Platform: UNKNOWN
Classifier: Programming Language :: Python :: 3
Classifier: License :: OSI Approved :: MIT License
Classifier: Operating System :: OS Independent
Requires-Python: >=3.9
License-File: LICENSE
Requires-Dist: numpy
Requires-Dist: pandas
Requires-Dist: scipy
Requires-Dist: dask
Requires-Dist: xarray
Requires-Dist: wget
Requires-Dist: netcdf4
Requires-Dist: pyopencl
Requires-Dist: matplotlib
Requires-Dist: tqdm
Requires-Dist: pytest
